package_name/__init__.py
package_name/file1_name.py
package_name/file2_name.py
package_test/__init__.py
package_test/file1_name.py
package_test/file2_name.py
package_test_python_estevam/__init__.py
package_test_python_estevam/file1_name.py
package_test_python_estevam/file2_name.py
package_test_python_estevam-0.0.1.dist-info/METADATA
package_test_python_estevam-0.0.1.dist-info/WHEEL
package_test_python_estevam-0.0.1.dist-info/top_level.txt
package_test_python_estevam-0.0.1.dist-info/RECORD
