Metadata-Version: 2.1
Name: package-test-python-estevam
Version: 0.0.1
Summary: My short description
Home-page: UNKNOWN
Author: Estevam
License: UNKNOWN
Platform: UNKNOWN
Requires-Python: >=3.8
